COPYING
MANIFEST.in
README.rst
buildout.cfg
requirements.txt
setup.py
version.txt
bob/__init__.py
bob.db.uvad.egg-info/PKG-INFO
bob.db.uvad.egg-info/SOURCES.txt
bob.db.uvad.egg-info/dependency_links.txt
bob.db.uvad.egg-info/entry_points.txt
bob.db.uvad.egg-info/requires.txt
bob.db.uvad.egg-info/top_level.txt
bob/db/__init__.py
bob/db/uvad/__init__.py
bob/db/uvad/config.py
bob/db/uvad/driver.py
bob/db/uvad/query.py
bob/db/uvad/test.py
bob/db/uvad/lists/experiment_1/dev/for_attack.lst
bob/db/uvad/lists/experiment_1/dev/for_real.lst
bob/db/uvad/lists/experiment_1/train/for_attack.lst
bob/db/uvad/lists/experiment_1/train/for_real.lst
bob/db/uvad/lists/experiment_1_1/dev/for_attack.lst
bob/db/uvad/lists/experiment_1_1/dev/for_real.lst
bob/db/uvad/lists/experiment_1_1/eval/for_attack.lst
bob/db/uvad/lists/experiment_1_1/eval/for_real.lst
bob/db/uvad/lists/experiment_1_1/train/for_attack.lst
bob/db/uvad/lists/experiment_1_1/train/for_real.lst
bob/db/uvad/lists/experiment_2_1/dev/for_attack.lst
bob/db/uvad/lists/experiment_2_1/dev/for_real.lst
bob/db/uvad/lists/experiment_2_1/train/for_attack.lst
bob/db/uvad/lists/experiment_2_1/train/for_real.lst
bob/db/uvad/lists/experiment_2_2/dev/for_attack.lst
bob/db/uvad/lists/experiment_2_2/dev/for_real.lst
bob/db/uvad/lists/experiment_2_2/train/for_attack.lst
bob/db/uvad/lists/experiment_2_2/train/for_real.lst
bob/db/uvad/lists/experiment_2_3/dev/for_attack.lst
bob/db/uvad/lists/experiment_2_3/dev/for_real.lst
bob/db/uvad/lists/experiment_2_3/train/for_attack.lst
bob/db/uvad/lists/experiment_2_3/train/for_real.lst
bob/db/uvad/lists/experiment_2_4/dev/for_attack.lst
bob/db/uvad/lists/experiment_2_4/dev/for_real.lst
bob/db/uvad/lists/experiment_2_4/train/for_attack.lst
bob/db/uvad/lists/experiment_2_4/train/for_real.lst
bob/db/uvad/lists/experiment_2_5/dev/for_attack.lst
bob/db/uvad/lists/experiment_2_5/dev/for_real.lst
bob/db/uvad/lists/experiment_2_5/train/for_attack.lst
bob/db/uvad/lists/experiment_2_5/train/for_real.lst
bob/db/uvad/lists/experiment_2_6/dev/for_attack.lst
bob/db/uvad/lists/experiment_2_6/dev/for_real.lst
bob/db/uvad/lists/experiment_2_6/train/for_attack.lst
bob/db/uvad/lists/experiment_2_6/train/for_real.lst
