Metadata-Version: 1.1
Name: bob.db.uvad
Version: 0.0.6
Summary: UVAD Database Access in Bob
Home-page: https://gitlab.idiap.ch/bob/bob.db.uvad
Author: Amir Mohammadi
Author-email: amir.mohammadi@idiap.ch
License: GPLv3
Keywords: bob
Platform: UNKNOWN
Classifier: Framework :: Bob
Classifier: Development Status :: 3 - Alpha
Classifier: Intended Audience :: Developers
Classifier: License :: OSI Approved :: GNU General Public License v3 (GPLv3)
Classifier: Natural Language :: English
Classifier: Programming Language :: Python
Classifier: Topic :: Scientific/Engineering :: Artificial Intelligence
